ase_hdf5/__init__.py
ase_hdf5/core.py
ase_hdf5/utils.py
ase_hdf5-0.1.6.dist-info/LICENSE.md
ase_hdf5-0.1.6.dist-info/METADATA
ase_hdf5-0.1.6.dist-info/WHEEL
ase_hdf5-0.1.6.dist-info/top_level.txt
ase_hdf5-0.1.6.dist-info/RECORD
