Metadata-Version: 2.1
Name: ase-hdf5
Version: 0.1.6
Summary: Reading and writing ASE trajectories to HDF5 files.
Author-email: Thomas C Nicholas <tcnicholas@me.com>
License: MIT License
Classifier: License :: OSI Approved :: MIT License
Classifier: Programming Language :: Python
Classifier: Programming Language :: Python :: 3
Classifier: Programming Language :: Python :: 3.8
Classifier: Programming Language :: Python :: 3.9
Classifier: Programming Language :: Python :: 3.10
Classifier: Programming Language :: Python :: 3.11
Classifier: Programming Language :: Python :: 3.12
Requires-Python: >=3.8
License-File: LICENSE.md
Requires-Dist: ase>=3.23.0
Requires-Dist: h5py>=3.11.0
Provides-Extra: dev
Requires-Dist: bumpver; extra == "dev"
Requires-Dist: ruff; extra == "dev"
Provides-Extra: publish
Requires-Dist: twine; extra == "publish"
Requires-Dist: build; extra == "publish"
Provides-Extra: tests
Requires-Dist: pytest; extra == "tests"
Requires-Dist: pytest-cov; extra == "tests"
